{
  "name": "Desktop",
  "version": "1.0.0",
  "description": "``` \r \"devDependencies\": {\r   \"@ersinfotech/merge\": \"^1.0.0\",\r   \"babel-cli\": \"^6.24.0\",\r   \"babel-core\": \"^6.26.3\",\r   \"babel-eslint\": \"^8.2.3\",\r   \"babel-jest\": \"^22.4.3\",\r   \"babel-loader\": \"^7.1.4\",\r   \"babel-plugin-import\": \"^1.7.0\",\r   \"babel-plugin-lodash\": \"^3.2.11\",\r   \"babel-plugin-transform-decorators-legacy\": \"^1.3.4\",\r   \"babel-plugin-transform-runtime\": \"^6.23.0\",\r   \"babel-preset-es2015\": \"^6.24.0\",\r   \"babel-preset-react\": \"^6.23.0\",\r   \"babel-preset-react-hmre\": \"^1.1.1\",\r   \"babel-preset-stage-0\": \"^6.22.0\",\r   \"babel-register\": \"^6.24.0\",\r   \"babel-runtime\": \"^6.22.0\",\r   \"bluebird\": \"^3.5.0\",\r   \"colors\": \"^1.2.4\",\r   \"cron\": \"^1.2.1\",\r   \"css-loader\": \"^0.28.11\",\r   \"es6-promise\": \"^4.2.4\",\r   \"eslint\": \"^4.19.1\",\r   \"eslint-plugin-babel\": \"^5.1.0\",\r   \"eslint-plugin-react\": \"^7.7.0\",\r   \"express\": \"^4.16.3\",\r   \"extract-text-webpack-plugin\": \"^4.0.0-beta.0\",\r   \"file-loader\": \"^1.1.11\",\r   \"html-webpack-plugin\": \"^3.2.0\",\r   \"imagemin-pngquant\": \"^5.1.0\",\r   \"isomorphic-fetch\": \"^2.2.1\",\r   \"jest\": \"^22.4.3\",\r   \"less\": \"^3.0.4\",\r   \"less-loader\": \"^4.1.0\",\r   \"marked\": \"^0.3.19\",\r   \"react-addons-test-utils\": \"^15.4.2\",\r   \"react-test-renderer\": \"^16.3.2\",\r   \"request\": \"^2.85.0\",\r   \"rimraf\": \"^2.5.4\",\r   \"style-loader\": \"^0.21.0\",\r   \"sw-precache-webpack-plugin\": \"^0.11.5\",\r   \"ts-loader\": \"^4.2.0\",\r   \"wangeditor\": \"^3.1.1\",\r   \"webpack\": \"^4.7.0\",\r   \"webpack-cli\": \"^2.1.3\",\r   \"webpack-dev-middleware\": \"^3.1.3\",\r   \"webpack-hot-middleware\": \"^2.22.1\",\r   \"yrui\": \"^1.7.41\"\r },\r \"dependencies\": {\r   \"antd\": \"^3.5.0\",\r   \"babel-polyfill\": \"^6.23.0\",\r   \"dva-cli\": \"^1.0.0-bea.2\",\r   \"echarts\": \"^4.1.0\",\r   \"font-awesome\": \"^4.7.0\",\r   \"imagemin-webpack-plugin\": \"^2.1.1\",\r   \"jquery\": \"^3.3.1\",\r   \"lodash\": \"^4.17.10\",\r   \"prop-types\": \"^15.6.1\",\r   \"react\": \"^16.3.2\",\r   \"react-contextmenu-yu\": \"^1.6.5\",\r   \"react-custom-scrollbars\": \"^4.1.2\",\r   \"react-dom\": \"^16.3.2\",\r   \"react-lazyload\": \"^2.2.7\",\r   \"react-redux\": \"^5.0.7\",\r   \"react-router\": \"^4.0.0\",\r   \"react-router-dom\": \"^4.0.0\",\r   \"redux\": \"^4.0.0\",\r   \"redux-logger\": \"^3.0.6\",\r   \"redux-promise\": \"^0.5.3\",\r   \"redux-thunk\": \"^2.2.0\"\r   }```",
  "main": "scripts/server.js",
  "directories": {
    "test": "test"
  },
  "scripts": {
    "dev": "webpack",
    "start": "node scripts/server.js",
    "build": "webpack --config scripts/webpack.production.js --progress",
    "lint": "eslint app/**/*.{js,jsx}",
    "precommit": "npm run lint"
  },
  "keywords": [],
  "author": "",
  "license": "ISC",
  "devDependencies": {
    "@ersinfotech/merge": "^1.0.0",
    "babel-cli": "^6.24.0",
    "babel-core": "^6.26.3",
    "babel-eslint": "^8.2.3",
    "babel-jest": "^22.4.3",
    "babel-loader": "^7.1.4",
    "babel-plugin-import": "^1.7.0",
    "babel-plugin-lodash": "^3.2.11",
    "babel-plugin-transform-decorators-legacy": "^1.3.4",
    "babel-plugin-transform-runtime": "^6.23.0",
    "babel-preset-es2015": "^6.24.0",
    "babel-preset-react": "^6.23.0",
    "babel-preset-react-hmre": "^1.1.1",
    "babel-preset-stage-0": "^6.22.0",
    "babel-register": "^6.24.0",
    "babel-runtime": "^6.22.0",
    "bluebird": "^3.5.0",
    "colors": "^1.2.4",
    "cron": "^1.2.1",
    "css-loader": "^0.28.11",
    "es6-promise": "^4.2.4",
    "eslint": "^4.19.1",
    "eslint-plugin-babel": "^5.1.0",
    "eslint-plugin-react": "^7.7.0",
    "express": "^4.16.3",
    "extract-text-webpack-plugin": "^4.0.0-beta.0",
    "file-loader": "^1.1.11",
    "html-loader": "^0.5.5",
    "html-webpack-plugin": "^3.2.0",
    "imagemin-pngquant": "^5.1.0",
    "isomorphic-fetch": "^2.2.1",
    "jest": "^22.4.3",
    "less": "^3.0.4",
    "less-loader": "^4.1.0",
    "marked": "^0.3.19",
    "raw-loader": "^0.5.1",
    "react-addons-test-utils": "^15.4.2",
    "react-test-renderer": "^16.3.2",
    "request": "^2.85.0",
    "rimraf": "^2.5.4",
    "style-loader": "^0.21.0",
    "sw-precache-webpack-plugin": "^0.11.5",
    "ts-loader": "^4.2.0",
    "wangeditor": "^3.1.1",
    "webpack": "4.7.0",
    "webpack-cli": "2.1.3",
    "webpack-dev-middleware": "^3.1.3",
    "webpack-hot-middleware": "^2.22.1",
    "yrui": "^1.7.41"
  },
  "dependencies": {
    "antd": "^3.10.9",
    "axios": "^0.18.0",
    "babel-polyfill": "^6.23.0",
    "braft-editor": "^2.3.7",
    "braft-extensions": "^0.0.18",
    "dva-cli": "^1.0.0-bea.2",
    "echarts": "^4.1.0",
    "font-awesome": "^4.7.0",
    "http-proxy-middleware": "^0.18.0",
    "imagemin-webpack-plugin": "^2.1.1",
    "jquery": "^3.3.1",
    "jquery-ui": "^1.12.1",
    "lodash": "^4.17.10",
    "prop-types": "^15.6.1",
    "qrcode.react": "^0.8.0",
    "rc-animate": "^2.8.2",
    "rc-tree": "^2.1.0",
    "rc-tree-select": "^2.9.1",
    "react": "^16.3.2",
    "react-avatar-editor": "^11.0.2",
    "react-color": "^2.17.3",
    "react-contextmenu-yu": "^1.6.5",
    "react-custom-scrollbars": "^4.1.2",
    "react-dev-utils": "^5.0.2",
    "react-dom": "^16.3.2",
    "react-draft-wysiwyg": "^1.12.13",
    "react-dropzone": "^4.2.9",
    "react-lazyload": "^2.2.7",
    "react-redux": "^5.0.7",
    "react-router": "^4.0.0",
    "react-router-dom": "^4.0.0",
    "react-zmage": "^0.4.0",
    "redux": "^4.0.0",
    "redux-logger": "^3.0.6",
    "redux-promise": "^0.5.3",
    "redux-saga": "^0.16.0",
    "redux-thunk": "^2.2.0",
    "reqwest": "^2.0.5",
    "spark-md5": "^3.0.0"
  },
  "repository": {
    "type": "git",
    "url": "https://gitfh.com/fh_youqu/youqums_front.git"
  }
}
